UmiTD/UmiTD.py
UmiTD/__init__.py
UmiTestData-0.2.dist-info/METADATA
UmiTestData-0.2.dist-info/WHEEL
UmiTestData-0.2.dist-info/top_level.txt
UmiTestData-0.2.dist-info/RECORD
